tmule/__init__.py
tmule/_compat.py
tmule/exc.py
tmule/formats.py
tmule/loader.py
tmule/tmule.py
tmule/tmux.py
tmule/ws_protocol.py
tmule/www/base.html
tmule/www/index.html
tmule/www/static/css/bootstrap-theme.css
tmule/www/static/css/bootstrap-theme.css.map
tmule/www/static/css/bootstrap-theme.min.css
tmule/www/static/css/bootstrap.css
tmule/www/static/css/bootstrap.css.map
tmule/www/static/css/bootstrap.min.css
tmule/www/static/fonts/glyphicons-halflings-regular.eot
tmule/www/static/fonts/glyphicons-halflings-regular.svg
tmule/www/static/fonts/glyphicons-halflings-regular.ttf
tmule/www/static/fonts/glyphicons-halflings-regular.woff
tmule/www/static/fonts/glyphicons-halflings-regular.woff2
tmule/www/static/js/autobahn.min.js
tmule/www/static/js/bootstrap.js
tmule/www/static/js/bootstrap.min.js
tmule/www/static/js/jquery.min.js
tmule/www/static/js/npm.js
tmule/www/static/js/reconnecting-websocket.min.js
tmule/www/static/js/webnsock.js
tmule-1.6.1.dist-info/licenses/LICENSE
tmule-1.6.1.dist-info/METADATA
tmule-1.6.1.dist-info/WHEEL
tmule-1.6.1.dist-info/entry_points.txt
tmule-1.6.1.dist-info/top_level.txt
tmule-1.6.1.dist-info/RECORD
